.DS_Store
csv2rst/__init__.py
csv2rst/csv2rst.py
formats/__init__.py
formats/csv2rst.py
formats/json2rst.py
funcs/__init__.py
funcs/command.py
funcs/funcs.py
json2rst/__init__.py
json2rst/json2rst.py
toRST/__init__.py
toRST/toRST.py
toRST/write.py
toRST-0.1.51.dist-info/LICENSE
toRST-0.1.51.dist-info/METADATA
toRST-0.1.51.dist-info/WHEEL
toRST-0.1.51.dist-info/entry_points.txt
toRST-0.1.51.dist-info/top_level.txt
toRST-0.1.51.dist-info/RECORD
