Metadata-Version: 2.1
Name: toRST
Version: 0.1.51
Summary: Command line tool for converting CSV and JSON files into reStructuredText Tables.
Home-page: https://github.com/jrey999/toRST
Author: John Reynolds
Author-email: reynoldsjohngreg@gmail.com
License: The MIT License (MIT)
Project-URL: Bug Tracker, https://github.com/jrey999/toRST/issues
Classifier: Programming Language :: Python :: 3
Classifier: License :: OSI Approved :: MIT License
Classifier: Operating System :: OS Independent
License-File: LICENSE
